pymasscode/README.md
pymasscode/__init__.py
pymasscode/dcls.py
pymasscode/loader.py
pymasscode/model.py
pymasscode/pyproject.toml
pymasscode/etc/clsprop.py
pymasscode/etc/fileProp.py
pymasscode/etc/tinydb_query.py
pymasscode/etc/utils.py
pymasscode-1.0.0b3.dist-info/METADATA
pymasscode-1.0.0b3.dist-info/WHEEL
pymasscode-1.0.0b3.dist-info/RECORD
